{
	"loop": {
		"ПOIЯD_ᴇʀʀᴏʀ_ɴᴏᴛ_Qᴜᴇᴜᴇ": "🦋𝗡𝗢𝗜𝗥✨𝗬𝗼𝘂𝗧𝘂𝗯𝗲𝗠𝘂𝘀𝗶𝗰 𝗣𝗹𝗮𝘆𝗲𝗿🦋✨\n•••-----------------------------------------•••\n\n>🦋𝗡𝗢𝗜𝗥  IS NOT PLAYING ANYMUSIC YET.....",
		"ПOIЯD_ʀᴇꜱᴜʟᴛ": "🦋𝗡𝗢𝗜𝗥✨𝗬𝗼𝘂𝗧𝘂𝗯𝗲𝗠𝘂𝘀𝗶𝗰 𝗣𝗹𝗮𝘆𝗲𝗿🦋✨\n•••-----------------------------------------•••\n\n>Loop is now turned**{loop}**"
	},
	"current": {
		"ПOIЯD_ᴇʀʀᴏʀ_ɴᴏᴛ_Qᴜᴇᴜᴇ": "🦋𝗡𝗢𝗜𝗥✨𝗬𝗼𝘂𝗧𝘂𝗯𝗲𝗠𝘂𝘀𝗶𝗰 𝗣𝗹𝗮𝘆𝗲𝗿🦋✨\n•••-----------------------------------------•••\n\n>🦋𝗡𝗢𝗜𝗥  IS NOT PLAYING ANYMUSIC YET.....",
		"ПOIЯD_ᴇᴍʙᴇᴅ_ᴛɪᴛʟᴇ": "🦋𝗡𝗢𝗜𝗥✨𝗬𝗼𝘂𝗧𝘂𝗯𝗲𝗠𝘂𝘀𝗶𝗰 𝗣𝗹𝗮𝘆𝗲𝗿🦋✨\n•••-----------------------------------------•••\n\n>🦋𝗡𝗢𝗜𝗥 - NOW PLAYING",
		"live": "🦋𝗡𝗢𝗜𝗥✨𝗬𝗼𝘂𝗧𝘂𝗯𝗲𝗠𝘂𝘀𝗶𝗰 𝗣𝗹𝗮𝘆𝗲𝗿🦋✨\n•••-----------------------------------------•••\n\n>🦋𝗡𝗢𝗜𝗥 - ◉LIVE",
		"timeRemaining": "🦋𝗡𝗢𝗜𝗥✨𝗬𝗼𝘂𝗧𝘂𝗯𝗲𝗠𝘂𝘀𝗶𝗰 𝗣𝗹𝗮𝘆𝗲𝗿🦋✨\n•••-----------------------------------------•••\n\n>⏱TIME REMAINING: {time}"
	},
	"pause": {
		"ПOIЯD_ᴇʀʀᴏʀ_ɴᴏᴛ_Qᴜᴇᴜᴇ": "🦋𝗡𝗢𝗜𝗥✨𝗬𝗼𝘂𝗧𝘂𝗯𝗲𝗠𝘂𝘀𝗶𝗰 𝗣𝗹𝗮𝘆𝗲𝗿🦋✨\n•••-----------------------------------------•••\n\n>🦋𝗡𝗢𝗜𝗥  IS NOT PLAYING ANYMUSIC YET.....",
		"ПOIЯD_ʀᴇꜱᴜʟᴛ": "<@{author}>🦋𝗡𝗢𝗜𝗥✨𝗬𝗼𝘂𝗧𝘂𝗯𝗲𝗠𝘂𝘀𝗶𝗰 𝗣𝗹𝗮𝘆𝗲𝗿🦋✨\n•••-----------------------------------------•••\n\n>🚦 PAUSED THE MUSIC."
	},
	"ping": {
		"ПOIЯD_ʀᴇꜱᴜʟᴛ": "🦋𝗡𝗢𝗜𝗥✨𝗬𝗼𝘂𝗧𝘂𝗯𝗲𝗠𝘂𝘀𝗶𝗰 𝗣𝗹𝗮𝘆𝗲𝗿🦋✨\n•••-----------------------------------------•••\n\n>⌛️AVERAGE PING OF 𝗡𝗢𝗜𝗥's SERVER: {ping}ms"
	},
	"play": {
		"ПOIЯD_ᴇʀʀᴏʀ_ɴᴏᴛ_ᴄʜᴀɴɴᴇʟ": "🦋𝗡𝗢𝗜𝗥✨𝗬𝗼𝘂𝗧𝘂𝗯𝗲𝗠𝘂𝘀𝗶𝗰 𝗣𝗹𝗮𝘆𝗲𝗿🦋✨\n•••-----------------------------------------•••\n\n>YOU NEED TO JOIN A VOICE CHANNEL FIRST!",
		"ПOIЯD_ᴇʀʀᴏʀ_ɴᴏᴛ_ɪɴ_ꜱᴀᴍᴇ_ᴄʜᴀɴɴᴇʟ": "🦋𝗡𝗢𝗜𝗥✨𝗬𝗼𝘂𝗧𝘂𝗯𝗲𝗠𝘂𝘀𝗶𝗰 𝗣𝗹𝗮𝘆𝗲𝗿🦋✨\n•••-----------------------------------------•••\n\n>YOU MUST BE IN THE SAME CHANNEL AS {user}",
		"ПOIЯD_ᴜꜱᴀɢᴇ_ʀᴇᴘʟʏ": "🦋𝗡𝗢𝗜𝗥✨𝗬𝗼𝘂𝗧𝘂𝗯𝗲𝗠𝘂𝘀𝗶𝗰 𝗣𝗹𝗮𝘆𝗲𝗿🦋✨\n•••-----------------------------------------•••\n\n>⚓️**USAGE:**{prefix}play <YouTube URL | Video Name",
		"ПOIЯD_ᴍɪꜱꜱɪɴɢ_ᴘᴇʀᴍɪꜱꜱɪᴏɴ_ᴄᴏɴɴᴇᴄᴛ": "🦋𝗡𝗢𝗜𝗥✨𝗬𝗼𝘂𝗧𝘂𝗯𝗲𝗠𝘂𝘀𝗶𝗰 𝗣𝗹𝗮𝘆𝗲𝗿🦋✨\n•••-----------------------------------------•••\n\n>CANNOT CONNECT TO VOICE CHANNEL, MISSING PERMISSIONS!",
		"ПOIЯD_ᴍɪꜱꜱɪɴɢ_ᴘᴇʀᴍɪꜱꜱɪᴏɴ_ꜱᴘᴇᴀᴋ": "🦋𝗡𝗢𝗜𝗥✨𝗬𝗼𝘂𝗧𝘂𝗯𝗲𝗠𝘂𝘀𝗶𝗰 𝗣𝗹𝗮𝘆𝗲𝗿🦋✨\n•••-----------------------------------------•••\n\n>I CANNOT SPEAK IN THIS VOICE CHANNEL, MAKE SURE I HAVE THE PROPER PERMISSIONS!",
		"ПOIЯD_Qᴜᴇᴜᴇ_ᴀᴅᴅᴇᴅ": "🦋𝗡𝗢𝗜𝗥✨𝗬𝗼𝘂𝗧𝘂𝗯𝗲𝗠𝘂𝘀𝗶𝗰 𝗣𝗹𝗮𝘆𝗲𝗿🦋✨\n•••-----------------------------------------•••\n\n>🍧**Song:** _{title}_\nHAS BEEN ADDED TO THE QUEUE BY <@{author}>",
		"ПOIЯD_ᴄᴀɴᴛ_ᴊᴏɪɴ_ᴄʜᴀɴɴᴇʟ": "🦋𝗡𝗢𝗜𝗥✨𝗬𝗼𝘂𝗧𝘂𝗯𝗲𝗠𝘂𝘀𝗶𝗰 𝗣𝗹𝗮𝘆𝗲𝗿🦋✨\n•••-----------------------------------------•••\n\n>COULD NOT JOIN THE CHANNEL: {error}",
		"ПOIЯD_Qᴜᴇᴜᴇ_ᴇɴᴅᴇᴅ": "🦋𝗡𝗢𝗜𝗥✨𝗬𝗼𝘂𝗧𝘂𝗯𝗲𝗠𝘂𝘀𝗶𝗰 𝗣𝗹𝗮𝘆𝗲𝗿🦋✨\n•••-----------------------------------------•••\n\n>❌ MUSIC QUEUE ENDED.",
		"ПOIЯD_Qᴜᴇᴜᴇ_ᴇʀʀᴏʀ": "🦋𝗡𝗢𝗜𝗥✨𝗬𝗼𝘂𝗧𝘂𝗯𝗲𝗠𝘂𝘀𝗶𝗰 𝗣𝗹𝗮𝘆𝗲𝗿🦋✨\n•••-----------------------------------------•••\n\n>**ERROR:** {error}",
		"ПOIЯD_ꜱᴛᴀʀᴛᴇᴅ_ᴘʟᴀʏɪɴɢ": "🦋𝗡𝗢𝗜𝗥✨𝗬𝗼𝘂𝗧𝘂𝗯𝗲𝗠𝘂𝘀𝗶𝗰 𝗣𝗹𝗮𝘆𝗲𝗿🦋✨\n•••-----------------------------------------•••\n\n>🍧**TITILE**: _{title}_\n>⛓**LINK**:  _{url}_",
		"ПOIЯD_ꜱᴋɪᴘ_ꜱᴏɴɢ": "<@{author}>🦋𝗡𝗢𝗜𝗥✨𝗬𝗼𝘂𝗧𝘂𝗯𝗲𝗠𝘂𝘀𝗶𝗰 𝗣𝗹𝗮𝘆𝗲𝗿🦋✨\n•••-----------------------------------------•••\n\n>⏩ SKIPPED THE SONG",
		"ПOIЯD_ᴘᴀᴜꜱᴇ_ꜱᴏɴɢ": "<@{author}>🦋𝗡𝗢𝗜𝗥✨𝗬𝗼𝘂𝗧𝘂𝗯𝗲𝗠𝘂𝘀𝗶𝗰 𝗣𝗹𝗮𝘆𝗲𝗿🦋✨\n•••-----------------------------------------•••\n\n>🚦 PAUSED THE MUSIC.",
		"ПOIЯD_ʀᴇꜱᴜᴍᴇ_ꜱᴏɴɢ": "<@{author}>🦋𝗡𝗢𝗜𝗥✨𝗬𝗼𝘂𝗧𝘂𝗯𝗲𝗠𝘂𝘀𝗶𝗰 𝗣𝗹𝗮𝘆𝗲𝗿🦋✨\n•••-----------------------------------------•••\n\n>▶ RESUMED THE MUSIC!",
		"ПOIЯD_ᴜɴᴍᴜᴛᴇᴅ_ꜱᴏɴɢ": "<@{author}>🦋𝗡𝗢𝗜𝗥✨𝗬𝗼𝘂𝗧𝘂𝗯𝗲𝗠𝘂𝘀𝗶𝗰 𝗣𝗹𝗮𝘆𝗲𝗿🦋✨\n•••-----------------------------------------•••\n\n>🔊 UNMUTED THE MUSIC!",
		"ПOIЯD_ᴍᴜᴛᴇᴅ_ꜱᴏɴɢ": "<@{author}>🦋𝗡𝗢𝗜𝗥✨𝗬𝗼𝘂𝗧𝘂𝗯𝗲𝗠𝘂𝘀𝗶𝗰 𝗣𝗹𝗮𝘆𝗲𝗿🦋✨\n•••-----------------------------------------•••\n\n>🤫 MUTED THE MUSIC!",
		"ПOIЯD_ᴅᴇᴄʀᴇᴀꜱᴇᴅ_ᴠᴏʟᴜᴍᴇ": "<@{author}>🦋𝗡𝗢𝗜𝗥✨𝗬𝗼𝘂𝗧𝘂𝗯𝗲𝗠𝘂𝘀𝗶𝗰 𝗣𝗹𝗮𝘆𝗲𝗿🦋✨\n•••-----------------------------------------•••\n\n>🔉 DECREASED THE VOLUME, THE VOLUME IS NOW {volume}%",
		"ПOIЯD_ɪɴᴄʀᴇᴀꜱᴇᴅ_ᴠᴏʟᴜᴍᴇ": "<@{author}>🦋𝗡𝗢𝗜𝗥✨𝗬𝗼𝘂𝗧𝘂𝗯𝗲𝗠𝘂𝘀𝗶𝗰 𝗣𝗹𝗮𝘆𝗲𝗿🦋✨\n•••-----------------------------------------•••\n\n>🔊 INCREASED THE VOLUME, THE VOLUME IS NOW {volume}%",
		"ПOIЯD_ʟᴏᴏᴘ_ꜱᴏɴɢ": "<@{author}>🦋𝗡𝗢𝗜𝗥✨𝗬𝗼𝘂𝗧𝘂𝗯𝗲𝗠𝘂𝘀𝗶𝗰 𝗣𝗹𝗮𝘆𝗲𝗿🦋✨\n•••-----------------------------------------•••\n\n>LOOP IS NOW {loop}",
		"ПOIЯD_ꜱᴛᴏᴘ_ꜱᴏɴɢ": "<@{author}>🦋𝗡𝗢𝗜𝗥✨𝗬𝗼𝘂𝗧𝘂𝗯𝗲𝗠𝘂𝘀𝗶𝗰 𝗣𝗹𝗮𝘆𝗲𝗿🦋✨\n•••-----------------------------------------•••\n\n>❌ STOPPED THE MUSIC!",
		"ПOIЯD_ʟᴇᴀᴠᴇ_ᴄʜᴀɴɴᴇʟ": "🦋𝗡𝗢𝗜𝗥✨𝗬𝗼𝘂𝗧𝘂𝗯𝗲𝗠𝘂𝘀𝗶𝗰 𝗣𝗹𝗮𝘆𝗲𝗿🦋✨\n•••-----------------------------------------•••\n\n>LEFT VOICE CHANNEL...",
		"ПOIЯD_ꜱᴏɴɢ_ɴᴏᴛ_ꜰᴏᴜɴᴅ": "🦋𝗡𝗢𝗜𝗥✨𝗬𝗼𝘂𝗧𝘂𝗯𝗲𝗠𝘂𝘀𝗶𝗰 𝗣𝗹𝗮𝘆𝗲𝗿🦋✨\n•••-----------------------------------------•••\n\n>AUDIO NOT FOUND"
	},
	"playlist": {
		"ПOIЯD_ᴜꜱᴀɢᴇꜱ_ʀᴇᴘʟʏ": "🦋𝗡𝗢𝗜𝗥✨𝗬𝗼𝘂𝗧𝘂𝗯𝗲𝗠𝘂𝘀𝗶𝗰 𝗣𝗹𝗮𝘆𝗲𝗿🦋✨\n•••-----------------------------------------•••\n\n>⚓️**USAGE:**{prefix}play <YouTube Playlist URL | Playlist Name>",
		"ПOIЯD_ᴇʀʀᴏʀ_ɴᴏᴛ_ᴄʜᴀɴɴᴇʟ": "🦋𝗡𝗢𝗜𝗥✨𝗬𝗼𝘂𝗧𝘂𝗯𝗲𝗠𝘂𝘀𝗶𝗰 𝗣𝗹𝗮𝘆𝗲𝗿🦋✨\n•••-----------------------------------------•••\n\n>YOU NEED TO JOIN A VOICE CHANNEL FIRST!",
		"ПOIЯD_ᴇʀʀᴏʀ_ɴᴏᴛ_ɪɴ_ꜱᴀᴍᴇ_ᴄʜᴀɴɴᴇʟ": "🦋𝗡𝗢𝗜𝗥✨𝗬𝗼𝘂𝗧𝘂𝗯𝗲𝗠𝘂𝘀𝗶𝗰 𝗣𝗹𝗮𝘆𝗲𝗿🦋✨\n•••-----------------------------------------•••\n\n>YOU MUST BE IN THE SAME CHANNEL AS {user}",
		"ПOIЯD_ᴍɪꜱꜱɪɴɢ_ᴘᴇʀᴍɪꜱꜱɪᴏɴ_ᴄᴏɴɴᴇᴄᴛ": "🦋𝗡𝗢𝗜𝗥✨𝗬𝗼𝘂𝗧𝘂𝗯𝗲𝗠𝘂𝘀𝗶𝗰 𝗣𝗹𝗮𝘆𝗲𝗿🦋✨\n•••-----------------------------------------•••\n\n>Cannot connect to voice channel, MISSING PERMISSIONS",
		"ПOIЯD_ᴍɪꜱꜱɪɴɢ_ᴘᴇʀᴍɪꜱꜱɪᴏɴ_ꜱᴘᴇᴀᴋ": "🦋𝗡𝗢𝗜𝗥✨𝗬𝗼𝘂𝗧𝘂𝗯𝗲𝗠𝘂𝘀𝗶𝗰 𝗣𝗹𝗮𝘆𝗲𝗿🦋✨\n•••-----------------------------------------•••\n\n>I CANNOT SPEAK IN THIS VOICE CHANNEL, MAKE SURE I HAVE THE PROPER PERMISSIONS!",
		"ПOIЯD_ᴇʀʀᴏʀ_ɴᴏᴛ_ꜰᴏᴜɴᴅ_ᴘʟᴀʏʟɪꜱᴛ": "🦋𝗡𝗢𝗜𝗥✨𝗬𝗼𝘂𝗧𝘂𝗯𝗲𝗠𝘂𝘀𝗶𝗰 𝗣𝗹𝗮𝘆𝗲𝗿🦋✨\n•••-----------------------------------------•••\n\n>❌PLAYLIST NOT FOUND",
		"ПOIЯD_ꜰᴇᴛᴄʜɪɴɢ_ᴘʟᴀʏʟɪꜱᴛ": "🦋𝗡𝗢𝗜𝗥✨𝗬𝗼𝘂𝗧𝘂𝗯𝗲𝗠𝘂𝘀𝗶𝗰 𝗣𝗹𝗮𝘆𝗲𝗿🦋✨\n•••-----------------------------------------•••\n\n>⌛ FETCHING THE PLAYLIST...",
		"ПOIЯD_ᴘʟᴀʏʟɪꜱᴛ_ᴄʜᴀʀ_ʟɪᴍɪᴛ": "🦋𝗡𝗢𝗜𝗥✨𝗬𝗼𝘂𝗧𝘂𝗯𝗲𝗠𝘂𝘀𝗶𝗰 𝗣𝗹𝗮𝘆𝗲𝗿🦋✨\n•••-----------------------------------------•••\n\n>\nPLAYLIST LARGER THAN CHARACTER LIMIT...",
		"ПOIЯD_ꜱᴛᴀʀᴛᴇᴅ_ᴘʟᴀʏʟɪꜱᴛ": "<@{author}>🦋𝗡𝗢𝗜𝗥✨𝗬𝗼𝘂𝗧𝘂𝗯𝗲𝗠𝘂𝘀𝗶𝗰 𝗣𝗹𝗮𝘆𝗲𝗿🦋✨\n•••-----------------------------------------•••\n\n>STARTED A PLAYLIST",
		"ПOIЯD_ᴄᴀɴᴛ_ᴊᴏɪɴ_ᴄʜᴀɴɴᴇʟ": "🦋𝗡𝗢𝗜𝗥✨𝗬𝗼𝘂𝗧𝘂𝗯𝗲𝗠𝘂𝘀𝗶𝗰 𝗣𝗹𝗮𝘆𝗲𝗿🦋✨\n•••-----------------------------------------•••\n\n>COULD NOT JOIN THE CHANNEL: {error}"
	},
	"pruning": {
		"ПOIЯD_ᴇʀʀᴏʀ_ᴡʀɪᴛɪɴɢ_ꜰɪʟᴇ": "🦋𝗡𝗢𝗜𝗥✨𝗬𝗼𝘂𝗧𝘂𝗯𝗲𝗠𝘂𝘀𝗶𝗰 𝗣𝗹𝗮𝘆𝗲𝗿🦋✨\n•••-----------------------------------------•••\n\n>There was an error writing to the file.",
		"ПOIЯD_ʀᴇꜱᴜʟᴛ": "🦋𝗡𝗢𝗜𝗥✨𝗬𝗼𝘂𝗧𝘂𝗯𝗲𝗠𝘂𝘀𝗶𝗰 𝗣𝗹𝗮𝘆𝗲𝗿🦋✨\n•••-----------------------------------------•••\n\n>Message pruning is {result}"
	},
	"queue": {
		"ПOIЯD_ᴍɪꜱꜱɪɴɢ_ᴘᴇʀᴍɪꜱꜱɪᴏɴ_ᴍᴇꜱꜱᴀɢᴇ": "🦋𝗡𝗢𝗜𝗥✨𝗬𝗼𝘂𝗧𝘂𝗯𝗲𝗠𝘂𝘀𝗶𝗰 𝗣𝗹𝗮𝘆𝗲𝗿🦋✨\n•••-----------------------------------------•••\n\n>MISSING PERMISSION TO MANAGE MESSAGES OR ADD REACTIONS",
		"ПOIЯD_ᴇʀʀᴏʀ_ɴᴏᴛ_Qᴜᴇᴜᴇ": "🦋𝗡𝗢𝗜𝗥✨𝗬𝗼𝘂𝗧𝘂𝗯𝗲𝗠𝘂𝘀𝗶𝗰 𝗣𝗹𝗮𝘆𝗲𝗿🦋✨\n•••-----------------------------------------•••\n\n>❌ **NOTHING PLAYING IN THIS SERVER**",
		"ПOIЯD_ᴄᴜʀʀᴇɴᴛ_ᴘᴀɢᴇ": "🦋𝗡𝗢𝗜𝗥✨𝗬𝗼𝘂𝗧𝘂𝗯𝗲𝗠𝘂𝘀𝗶𝗰 𝗣𝗹𝗮𝘆𝗲𝗿🦋✨\n•••-----------------------------------------•••\n\n>🦋𝗡𝗢𝗜𝗥 - CURRENT PAGE - ",
		"ПOIЯD_ᴇᴍʙᴇᴅ_ᴛɪᴛʟᴇ": "🦋𝗡𝗢𝗜𝗥✨𝗬𝗼𝘂𝗧𝘂𝗯𝗲𝗠𝘂𝘀𝗶𝗰 𝗣𝗹𝗮𝘆𝗲𝗿🦋✨\n•••-----------------------------------------•••\n\n>🦋𝗡𝗢𝗜𝗥 - SONG QUEUE\n",
		"ПOIЯD_ᴇᴍʙᴇᴅ_ᴄᴜʀʀᴇɴᴛ_ꜱᴏɴɢ": "🦋𝗡𝗢𝗜𝗥✨𝗬𝗼𝘂𝗧𝘂𝗯𝗲𝗠𝘂𝘀𝗶𝗰 𝗣𝗹𝗮𝘆𝗲𝗿🦋✨\n•••-----------------------------------------•••\n\n>**Current Song - [{title}]({url})**\n\n>{info}"
	},
	"remove": {
		"ПOIЯD_ᴇʀʀᴏʀ_ɴᴏᴛ_Qᴜᴇᴜᴇ": "🦋𝗡𝗢𝗜𝗥✨𝗬𝗼𝘂𝗧𝘂𝗯𝗲𝗠𝘂𝘀𝗶𝗰 𝗣𝗹𝗮𝘆𝗲𝗿🦋✨\n•••-----------------------------------------•••\n\n>🦋𝗡𝗢𝗜𝗥 - THERE IS NO QUEUE.",
		"ПOIЯD_ᴜꜱᴀɢᴇ_ʀᴇᴘʟʏ": "🦋𝗡𝗢𝗜𝗥✨𝗬𝗼𝘂𝗧𝘂𝗯𝗲𝗠𝘂𝘀𝗶𝗰 𝗣𝗹𝗮𝘆𝗲𝗿🦋✨\n•••-----------------------------------------•••\n\n>⚓️**USAGE:**{prefix}remove <Queue Number>",
		"ПOIЯD_ʀᴇꜱᴜʟᴛ": "<@{author}>🦋𝗡𝗢𝗜𝗥✨𝗬𝗼𝘂𝗧𝘂𝗯𝗲𝗠𝘂𝘀𝗶𝗰 𝗣𝗹𝗮𝘆𝗲𝗿🦋✨\n•••-----------------------------------------•••\n\n>❌ Removed **{title}** from the queue."
	},
	"resume": {
		"ПOIЯD_ᴇʀʀᴏʀ_ɴᴏᴛ_Qᴜᴇᴜᴇ": "🦋𝗡𝗢𝗜𝗥✨𝗬𝗼𝘂𝗧𝘂𝗯𝗲𝗠𝘂𝘀𝗶𝗰 𝗣𝗹𝗮𝘆𝗲𝗿🦋✨\n•••-----------------------------------------•••\n\n>🦋𝗡𝗢𝗜𝗥 - IS NOT PLAYING ANYMUSIC YET.....",
		"ПOIЯD_ʀᴇꜱᴜʟᴛ_ɴᴏᴛ_ᴘʟᴀʏɪɴɢ": "<@{author}>🦋𝗡𝗢𝗜𝗥✨𝗬𝗼𝘂𝗧𝘂𝗯𝗲𝗠𝘂𝘀𝗶𝗰 𝗣𝗹𝗮𝘆𝗲𝗿🦋✨\n•••-----------------------------------------•••\n\n>▶ Resumed the music!",
		"ПOIЯD_ᴇʀʀᴏʀ_ᴘʟᴀʏɪɴɢ": "🦋𝗡𝗢𝗜𝗥✨𝗬𝗼𝘂𝗧𝘂𝗯𝗲𝗠𝘂𝘀𝗶𝗰 𝗣𝗹𝗮𝘆𝗲𝗿🦋✨\n•••-----------------------------------------•••\n\n>🦋𝗡𝗢𝗜𝗥 - THE QUEUE IS NOT PAUSED."
	},
	"shuffle": {
		"ПOIЯD_ᴇʀʀᴏʀ_ɴᴏᴛ_Qᴜᴇᴜᴇ": "🦋𝗡𝗢𝗜𝗥✨𝗬𝗼𝘂𝗧𝘂𝗯𝗲𝗠𝘂𝘀𝗶𝗰 𝗣𝗹𝗮𝘆𝗲𝗿🦋✨\n•••-----------------------------------------•••\n\n>🦋𝗡𝗢𝗜𝗥 - THERE IS NO QUEUE.",
		"ПOIЯD_ʀᴇꜱᴜʟᴛ": "<@{author}>🦋𝗡𝗢𝗜𝗥✨𝗬𝗼𝘂𝗧𝘂𝗯𝗲𝗠𝘂𝘀𝗶𝗰 𝗣𝗹𝗮𝘆𝗲𝗿🦋✨\n•••-----------------------------------------•••\n\n>🔀 SHUFFLED THE QUEUE"
	},
	"skip": {
		"ПOIЯD_ᴇʀʀᴏʀ_ɴᴏᴛ_Qᴜᴇᴜᴇ": "🦋𝗡𝗢𝗜𝗥✨𝗬𝗼𝘂𝗧𝘂𝗯𝗲𝗠𝘂𝘀𝗶𝗰 𝗣𝗹𝗮𝘆𝗲𝗿🦋✨\n•••-----------------------------------------•••\n\n>🦋𝗡𝗢𝗜𝗥 - THERE IS NOTHING PLAYING THAT I COULD SKIP FOR YOU.",
		"ПOIЯD_ʀᴇꜱᴜʟᴛ": "<@{author}>🦋𝗡𝗢𝗜𝗥✨𝗬𝗼𝘂𝗧𝘂𝗯𝗲𝗠𝘂𝘀𝗶𝗰 𝗣𝗹𝗮𝘆𝗲𝗿🦋✨\n•••-----------------------------------------•••\n\n>👉🏻 SKIPPED THE SONG"
	},
	"skipto": {
		"ПOIЯD_ᴜꜱᴀɢᴇ_ʀᴇᴘʟʏ": "🦋𝗡𝗢𝗜𝗥✨𝗬𝗼𝘂𝗧𝘂𝗯𝗲𝗠𝘂𝘀𝗶𝗰 𝗣𝗹𝗮𝘆𝗲𝗿🦋✨\n•••-----------------------------------------•••\n\n>⚓️**USAGE:**{prefix}{name} <Queue Number>",
		"ПOIЯD_ᴇʀʀᴏʀ_ɴᴏᴛ_Qᴜᴇᴜᴇ": "🦋𝗡𝗢𝗜𝗥✨𝗬𝗼𝘂𝗧𝘂𝗯𝗲𝗠𝘂𝘀𝗶𝗰 𝗣𝗹𝗮𝘆𝗲𝗿🦋✨\n•••-----------------------------------------•••\n\n>🦋𝗡𝗢𝗜𝗥 - THERE IS NO QUEUE.",
		"ПOIЯD_ᴇʀʀᴏʀ_ɴᴏᴛ_ᴠᴀʟɪᴅ": "🦋𝗡𝗢𝗜𝗥✨𝗬𝗼𝘂𝗧𝘂𝗯𝗲𝗠𝘂𝘀𝗶𝗰 𝗣𝗹𝗮𝘆𝗲𝗿🦋✨\n•••-----------------------------------------•••\n\n>🦋𝗡𝗢𝗜𝗥 - THE QUEUE IS ONLY {length} SONGS LONG!",
		"ПOIЯD_ʀᴇꜱᴜʟᴛ": "<@{author}>🦋𝗡𝗢𝗜𝗥✨𝗬𝗼𝘂𝗧𝘂𝗯𝗲𝗠𝘂𝘀𝗶𝗰 𝗣𝗹𝗮𝘆𝗲𝗿🦋✨\n•••-----------------------------------------•••\n\n>👉🏻 SKIPPED {arg} SONGS"
	},
	"stop": {
		"ПOIЯD_ᴇʀʀᴏʀ_ɴᴏᴛ_Qᴜᴇᴜᴇ": "🦋𝗡𝗢𝗜𝗥✨𝗬𝗼𝘂𝗧𝘂𝗯𝗲𝗠𝘂𝘀𝗶𝗰 𝗣𝗹𝗮𝘆𝗲𝗿🦋✨\n•••-----------------------------------------•••\n\n>🦋𝗡𝗢𝗜𝗥 - IS NOT PLAYING ANYMUSIC YET.....",
		"ПOIЯD_ʀᴇꜱᴜʟᴛ": "<@{author}>🦋𝗡𝗢𝗜𝗥✨𝗬𝗼𝘂𝗧𝘂𝗯𝗲𝗠𝘂𝘀𝗶𝗰 𝗣𝗹𝗮𝘆𝗲𝗿🦋✨\n•••-----------------------------------------•••\n\n>❌ stopped the music!"
	},
	"volume": {
		"ПOIЯD_ᴇʀʀᴏʀ_ɴᴏᴛ_Qᴜᴇᴜᴇ": "🦋𝗡𝗢𝗜𝗥✨𝗬𝗼𝘂𝗧𝘂𝗯𝗲𝗠𝘂𝘀𝗶𝗰 𝗣𝗹𝗮𝘆𝗲𝗿🦋✨\n•••-----------------------------------------•••\n\n>🦋𝗡𝗢𝗜𝗥 - IS NOT PLAYING ANYMUSIC YET.....",
		"ПOIЯD_ᴇʀʀᴏʀ_ɴᴏᴛ_ᴄʜᴀɴɴᴇʟ": "🦋𝗡𝗢𝗜𝗥✨𝗬𝗼𝘂𝗧𝘂𝗯𝗲𝗠𝘂𝘀𝗶𝗰 𝗣𝗹𝗮𝘆𝗲𝗿🦋✨\n•••-----------------------------------------•••\n\n>YOU NEED TO JOIN A VOICE CHANNEL FIRST!",
		"ПOIЯD_ᴄᴜʀʀᴇɴᴛ_ᴠᴏʟᴜᴍᴇ": "🦋𝗡𝗢𝗜𝗥✨𝗬𝗼𝘂𝗧𝘂𝗯𝗲𝗠𝘂𝘀𝗶𝗰 𝗣𝗹𝗮𝘆𝗲𝗿🦋✨\n•••-----------------------------------------•••\n\n>🔊 **THE CURRENT VOLUME IS:** `{volume}%`",
		"ПOIЯD_ᴇʀʀᴏʀ_ɴᴏᴛ_ɴᴜᴍʙᴇʀ": "🦋𝗡𝗢𝗜𝗥✨𝗬𝗼𝘂𝗧𝘂𝗯𝗲𝗠𝘂𝘀𝗶𝗰 𝗣𝗹𝗮𝘆𝗲𝗿🦋✨\n•••-----------------------------------------•••\n\n>🦋𝗡𝗢𝗜𝗥 - PLEASE USE A NUMBER TO SET VOLUME.",
		"ПOIЯD_ᴇʀʀᴏʀ_ɴᴏᴛ_ᴠᴀʟɪᴅ": "🦋𝗡𝗢𝗜𝗥✨𝗬𝗼𝘂𝗧𝘂𝗯𝗲𝗠𝘂𝘀𝗶𝗰 𝗣𝗹𝗮𝘆𝗲𝗿🦋✨\n•••-----------------------------------------•••\n\n>🦋𝗡𝗢𝗜𝗥 - PLEASE USE A NUMBER BETWEEN 0 - 100.",
		"ПOIЯD_ʀᴇꜱᴜʟᴛ": "🦋𝗡𝗢𝗜𝗥✨𝗬𝗼𝘂𝗧𝘂𝗯𝗲𝗠𝘂𝘀𝗶𝗰 𝗣𝗹𝗮𝘆𝗲𝗿🦋✨\n•••-----------------------------------------•••\n\n>🦋𝗡𝗢𝗜𝗥 - VOLUME SET TO: **{arg}%**"
	},
	"common": {
		"on": "🦋𝗡𝗢𝗜𝗥✨𝗬𝗼𝘂𝗧𝘂𝗯𝗲𝗠𝘂𝘀𝗶𝗰 𝗣𝗹𝗮𝘆𝗲𝗿🦋✨\n•••-----------------------------------------•••\n\n>🦋𝗡𝗢𝗜𝗥 - **TURNED ON**",
		"off": "🦋𝗡𝗢𝗜𝗥✨𝗬𝗼𝘂𝗧𝘂𝗯𝗲𝗠𝘂𝘀𝗶𝗰 𝗣𝗹𝗮𝘆𝗲𝗿🦋✨\n•••-----------------------------------------•••\n\n>🦋𝗡𝗢𝗜𝗥 - **TURNED OFF**",
		"ПOIЯD_ᴇɴᴀʙʟᴇᴅ": "🦋𝗡𝗢𝗜𝗥✨𝗬𝗼𝘂𝗧𝘂𝗯𝗲𝗠𝘂𝘀𝗶𝗰 𝗣𝗹𝗮𝘆𝗲𝗿🦋✨\n•••-----------------------------------------•••\n\n>🦋𝗡𝗢𝗜𝗥 - **HAS BEEN ENABLED**",
		"ПOIЯD_ᴅɪꜱᴀʙʟᴇᴅ": "🦋𝗡𝗢𝗜𝗥✨𝗬𝗼𝘂𝗧𝘂𝗯𝗲𝗠𝘂𝘀𝗶𝗰 𝗣𝗹𝗮𝘆𝗲𝗿🦋✨\n•••-----------------------------------------•••\n\n>🦋𝗡𝗢𝗜𝗥 - **HAS BEEN DISABLED**",
		"ПOIЯD_ᴇʀʀᴏʀ_ɴᴏᴛ_ᴄʜᴀɴɴᴇʟ": "🦋𝗡𝗢𝗜𝗥✨𝗬𝗼𝘂𝗧𝘂𝗯𝗲𝗠𝘂𝘀𝗶𝗰 𝗣𝗹𝗮𝘆𝗲𝗿🦋✨\n•••-----------------------------------------•••\n\n>🦋𝗡𝗢𝗜𝗥 - YOU NEED TO JOIN A VOICE CHANNEL first!",
		"ПOIЯD_ᴄᴏᴏʟᴅᴏᴡɴ_ᴍᴇꜱꜱᴀɢᴇ": "🦋𝗡𝗢𝗜𝗥✨𝗬𝗼𝘂𝗧𝘂𝗯𝗲𝗠𝘂𝘀𝗶𝗰 𝗣𝗹𝗮𝘆𝗲𝗿🦋✨\n•••-----------------------------------------•••\n\n>🦋𝗡𝗢𝗜𝗥 - PLEASE WAIT {time} MORE SECOND(s) BEFORE REUSING THE `{name}` COMMAND.",
		"ПOIЯD_ᴇʀʀᴏʀ_ᴄᴏᴍᴍᴀɴᴅ": "🦋𝗡𝗢𝗜𝗥✨𝗬𝗼𝘂𝗧𝘂𝗯𝗲𝗠𝘂𝘀𝗶𝗰 𝗣𝗹𝗮𝘆𝗲𝗿🦋✨\n•••-----------------------------------------•••\n\n>🦋𝗡𝗢𝗜𝗥 - THERE WAS AN ERROR EXECUTING THAT COMMAND."
	}
}